django_scrub_pii-1.1.3.dist-info/DESCRIPTION.rst
django_scrub_pii-1.1.3.dist-info/METADATA
django_scrub_pii-1.1.3.dist-info/RECORD
django_scrub_pii-1.1.3.dist-info/WHEEL
django_scrub_pii-1.1.3.dist-info/entry_points.txt
django_scrub_pii-1.1.3.dist-info/metadata.json
django_scrub_pii-1.1.3.dist-info/top_level.txt
scrubpii/__init__.py
scrubpii/__init__.pyc
scrubpii/models.py
scrubpii/models.pyc
scrubpii/utils.py
scrubpii/utils.pyc
scrubpii/__pycache__/__init__.cpython-34.pyc
scrubpii/__pycache__/models.cpython-34.pyc
scrubpii/__pycache__/utils.cpython-34.pyc
scrubpii/management/__init__.py
scrubpii/management/__init__.pyc
scrubpii/management/__pycache__/__init__.cpython-34.pyc
scrubpii/management/commands/__init__.py
scrubpii/management/commands/__init__.pyc
scrubpii/management/commands/get_sensitive_data_removal_script.py
scrubpii/management/commands/get_sensitive_data_removal_script.pyc
scrubpii/management/commands/__pycache__/__init__.cpython-34.pyc
scrubpii/management/commands/__pycache__/get_sensitive_data_removal_script.cpython-34.pyc
tests/__init__.py
tests/settings.py
tests/settings_postgres.py
tests/test_export.py
tests/urls.py
tests/testapp/__init__.py
tests/testapp/models.py
tests/testapp/sensitive_models.py
