Metadata-Version: 2.0
Name: django-scrub-pii
Version: 1.1.3
Summary: A django add-on that allows models to be decorated with information about which fields contain sensitive information, and an associated management command that creates a script to remove that information.
Home-page: UNKNOWN
Author: Matthew Wilkes
Author-email: matt@matthewwilkes.name
License: BSD
Platform: UNKNOWN
Classifier: Programming Language :: Python
Requires-Dist: django (==1.8)
Requires-Dist: setuptools
Provides-Extra: development
Requires-Dist: check-manifest; extra == 'development'
Requires-Dist: zest.releaser; extra == 'development'
Provides-Extra: test
Requires-Dist: coverage; extra == 'test'
Requires-Dist: flake8; extra == 'test'
Requires-Dist: nose; extra == 'test'
Requires-Dist: nose-selecttests; extra == 'test'
Requires-Dist: unittest2; extra == 'test'
